<annotation>
	<folder>WDJ_images</folder>
	<filename>47.jpg</filename>
	<path>C:\Users\Administrator\Downloads\WDJ_images\47.jpg</path>
	<source>
		<database>Unknown</database>
	</source>
	<size>
		<width>1080</width>
		<height>742</height>
		<depth>3</depth>
	</size>
	<segmented>0</segmented>
	<object>
		<name>WDJ</name>
		<pose>Unspecified</pose>
		<truncated>0</truncated>
		<difficult>0</difficult>
		<bndbox>
			<xmin>434</xmin>
			<ymin>63</ymin>
			<xmax>506</xmax>
			<ymax>165</ymax>
		</bndbox>
	</object>
</annotation>
